fsactl/__init__.py
fsactl/addons.py
fsactl/app.py
fsactl/downlaod.py
fsactl/errors.py
fsactl/handlers/__init__.py
fsactl/handlers/git.py
fsactl/handlers/yaml.py
fsactl/install.py
fsactl/make.py
fsactl/typing.py
fsactl/update.py
fsactl/workers/__init__.py
fsactl/workers/git.py
fsactl/workers/worker.py
fsactl-0.1.3.dist-info/entry_points.txt
fsactl-0.1.3.dist-info/LICENSE.txt
fsactl-0.1.3.dist-info/WHEEL
fsactl-0.1.3.dist-info/METADATA
fsactl-0.1.3.dist-info/RECORD
