Metadata-Version: 2.1
Name: fsactl
Version: 0.1.3
Summary: Install and update MSFS2020 addons
Home-page: https://michaelsasser.github.io/fsactl/index.html
License: GPL-3.0+
Keywords: FlightSimulator,FS2020,MSFS2020,Flight,Simulator,Addon,AddonManager
Author: Michael Sasser
Author-email: Michael@MichaelSasser.org
Requires-Python: >=3.9,<4.0
Classifier: Development Status :: 3 - Alpha
Classifier: Environment :: Console
Classifier: Environment :: Win32 (MS Windows)
Classifier: Intended Audience :: End Users/Desktop
Classifier: License :: OSI Approved :: GNU General Public License v3 or later (GPLv3+)
Classifier: Natural Language :: English
Classifier: Operating System :: Microsoft :: Windows
Classifier: Operating System :: Microsoft :: Windows :: Windows 10
Classifier: Programming Language :: Python :: 3
Classifier: Programming Language :: Python :: 3 :: Only
Classifier: Programming Language :: Python :: 3.9
Classifier: Topic :: Games/Entertainment
Classifier: Topic :: Games/Entertainment :: Simulation
Classifier: Typing :: Typed
Provides-Extra: docs
Requires-Dist: GitPython (>=3.1.11,<4.0.0)
Requires-Dist: Jinja2 (>=2.11.2,<3.0.0)
Requires-Dist: PyYaml (>=5.3.1,<6.0.0)
Requires-Dist: coloredlogs (>=14.0,<15.0)
Requires-Dist: semver (>=2.13.0,<3.0.0)
Requires-Dist: sphinx (>=3.3.1,<4.0.0); extra == "docs"
Requires-Dist: sphinx-autodoc-typehints (>=1.11.1,<2.0.0); extra == "docs"
Requires-Dist: sphinx_rtd_theme (>=0.5.0,<0.6.0); extra == "docs"
Requires-Dist: sphinxcontrib-programoutput (>=0.16,<0.17); extra == "docs"
Requires-Dist: tabulate (>=0.8.7,<0.9.0)
Project-URL: Documentation, https://michaelsasser.github.io/fsactl/index.html
Project-URL: Repository, https://github.com/MichaelSasser/fsactl
